dynamic_table/__init__.py
dynamic_table/table.py
dynamic_table_utils-0.1.0.dist-info/licenses/LICENSE
dynamic_table_utils-0.1.0.dist-info/METADATA
dynamic_table_utils-0.1.0.dist-info/WHEEL
dynamic_table_utils-0.1.0.dist-info/top_level.txt
dynamic_table_utils-0.1.0.dist-info/RECORD
