Metadata-Version: 2.4
Name: dynamic-table-utils
Version: 0.1.0
Summary: A Python package for creating dynamic tables at runtime
Author-email: Bevara Jnaneswara Rao <jnanesh.janu.b@gmail.com>
License: MIT
Project-URL: Homepage, https://github.com/JnaneswaraRao123/dynamic-table-utils
Requires-Python: >=3.7
License-File: LICENSE
Dynamic: license-file
